lddcollect/__init__.py
lddcollect/__main__.py
lddcollect/vendor/__init__.py
lddcollect/vendor/lddtree.py
lddcollect-0.2.0.dist-info/METADATA
lddcollect-0.2.0.dist-info/WHEEL
lddcollect-0.2.0.dist-info/entry_points.txt
lddcollect-0.2.0.dist-info/top_level.txt
lddcollect-0.2.0.dist-info/zip-safe
lddcollect-0.2.0.dist-info/RECORD
