Metadata-Version: 2.1
Name: lddcollect
Version: 0.2.0
Summary: List files/debian packages used by a Linux binary/dll
Home-page: https://github.com/kirill888/lddcollect
Author: Kirill Kouzoubov
Author-email: kirill888@gmail.com
License: MIT License
Keywords: ldd,elf
Platform: UNKNOWN
Classifier: Intended Audience :: Developers
Classifier: Development Status :: 5 - Production/Stable
Classifier: Operating System :: OS Independent
Classifier: License :: OSI Approved :: MIT License
Classifier: Programming Language :: Python :: 3.6
Classifier: Programming Language :: Python :: 3.7
Classifier: Programming Language :: Python :: 3.8
Requires-Python: >=3.6
Requires-Dist: click
Requires-Dist: pyelftools (>=0.24)
Provides-Extra: dev
Requires-Dist: wheel ; extra == 'dev'
Provides-Extra: test
Requires-Dist: pytest ; extra == 'test'
